pyt/__init__.py
pyt/__main__.py
pyt/compat.py
pyt/environ.py
pyt/path.py
pyt/tester.py
pyt/utils.py
pyt-1.3.0.dist-info/licenses/LICENSE.txt
pyt-1.3.0.dist-info/METADATA
pyt-1.3.0.dist-info/WHEEL
pyt-1.3.0.dist-info/entry_points.txt
pyt-1.3.0.dist-info/top_level.txt
pyt-1.3.0.dist-info/RECORD
