Metadata-Version: 2.4
Name: pyt
Version: 1.3.0
Summary: easily run python unit tests
Author-email: Jay Marcyes <jay@marcyes.com>
License-Expression: MIT
Project-URL: Homepage, http://github.com/Jaymon/pyt
Project-URL: Repository, https://github.com/Jaymon/pyt
Classifier: Development Status :: 4 - Beta
Classifier: Environment :: Console
Classifier: Intended Audience :: Developers
Classifier: Operating System :: OS Independent
Classifier: Topic :: Software Development :: Testing
Classifier: Programming Language :: Python :: 3
Requires-Python: >=3.10
License-File: LICENSE.txt
Provides-Extra: tests
Requires-Dist: testdata; extra == "tests"
Dynamic: license-file
